aero_data_ai/__init__.py
aero_data_ai/project_paths.json
aero_data_ai/project_paths.py
aero_data_ai-0.0.1.dist-info/METADATA
aero_data_ai-0.0.1.dist-info/WHEEL
aero_data_ai-0.0.1.dist-info/top_level.txt
aero_data_ai-0.0.1.dist-info/RECORD
