Metadata-Version: 2.1
Name: aero-data-ai
Version: 0.0.1
Summary: The official project path management library published by team Aero Data AI @InvoLead.
Author: Team Aero Data AI
Author-email: akshat.gupta@involead.com
Classifier: Programming Language :: Python :: 3
Classifier: License :: OSI Approved :: MIT License
Classifier: Operating System :: OS Independent
Requires-Python: >=3
